polars_bio/__init__.py
polars_bio/_metadata.py
polars_bio/constants.py
polars_bio/context.py
polars_bio/exceptions.py
polars_bio/interval_op_helpers.py
polars_bio/io.py
polars_bio/logging.py
polars_bio/operations.py
polars_bio/polars_bio.pypy311-pp73-x86_64-linux-gnu.so
polars_bio/polars_ext.py
polars_bio/predicate_translator.py
polars_bio/range_op.py
polars_bio/range_op_helpers.py
polars_bio/range_op_io.py
polars_bio/range_utils.py
polars_bio/sql.py
polars_bio/sql_predicate_builder.py
polars_bio/utils.py
polars_bio-0.20.1.dist-info/METADATA
polars_bio-0.20.1.dist-info/WHEEL
polars_bio-0.20.1.dist-info/licenses/LICENSE
polars_bio-0.20.1.dist-info/RECORD
