Metadata-Version: 2.4
Name: polars-bio
Version: 0.20.1
Classifier: Programming Language :: Rust
Classifier: Programming Language :: Python :: Implementation :: CPython
Classifier: Programming Language :: Python :: Implementation :: PyPy
Requires-Dist: polars>=1.37.1
Requires-Dist: pyarrow>=21.0.0,<22
Requires-Dist: datafusion>=50.0.0,<51
Requires-Dist: tqdm>=4.67.0,<5
Requires-Dist: typing-extensions>=4.14.0,<5
Requires-Dist: mkdocs-glightbox>=0.5.1,<1
Requires-Dist: polars-config-meta>=0.3.0,<1
Requires-Dist: pandas ; extra == 'pandas'
Requires-Dist: bioframe ; extra == 'viz'
Requires-Dist: matplotlib ; extra == 'viz'
Provides-Extra: pandas
Provides-Extra: viz
License-File: LICENSE
Summary: Blazing fast genomic operations on large Python dataframes
Requires-Python: >=3.10
